set.py
SimpleThreading/Threadingbyfunction.py
SimpleThreading/Threadpool.py
SimpleThreading/__init__.py
ThreadDownloader1307.egg-info/PKG-INFO
ThreadDownloader1307.egg-info/SOURCES.txt
ThreadDownloader1307.egg-info/dependency_links.txt
ThreadDownloader1307.egg-info/top_level.txt