Metadata-Version: 1.0
Name: ThreadDownloader1307
Version: 0.0.0
Summary: My first python distribution
Home-page: UNKNOWN
Author: UNKNOWN
Author-email: UNKNOWN
License: UNKNOWN
Platform: UNKNOWN
